setup.py
gausino_probability/Binomialdistribution.py
gausino_probability/Gaussiandistribution.py
gausino_probability/Generaldistribution.py
gausino_probability/__init__.py
gausino_probability.egg-info/PKG-INFO
gausino_probability.egg-info/SOURCES.txt
gausino_probability.egg-info/dependency_links.txt
gausino_probability.egg-info/not-zip-safe
gausino_probability.egg-info/top_level.txt